cognet/.gitattributes
cognet/__init__.py
cognet/cognet.py
cognet/dataFormatter.py
cognet/model.py
cognet/util.py
cognet/viz.py
cognet/.ipynb_checkpoints/__init__-checkpoint.py
cognet/.ipynb_checkpoints/cognet-checkpoint.py
cognet/.ipynb_checkpoints/dataFormatter-checkpoint.py
cognet/.ipynb_checkpoints/model-checkpoint.py
cognet/__pycache__/__init__.cpython-310.pyc
cognet/__pycache__/__init__.cpython-37.pyc
cognet/__pycache__/__init__.cpython-39.pyc
cognet/__pycache__/cognet.cpython-310.pyc
cognet/__pycache__/cognet.cpython-37.pyc
cognet/__pycache__/cognet.cpython-39.pyc
cognet/__pycache__/cognet_.cpython-37.pyc
cognet/__pycache__/dataFormatter.cpython-310.pyc
cognet/__pycache__/dataFormatter.cpython-37.pyc
cognet/__pycache__/dataFormatter.cpython-39.pyc
cognet/__pycache__/model.cpython-310.pyc
cognet/__pycache__/model.cpython-37.pyc
cognet/__pycache__/model.cpython-39.pyc
cognet/__pycache__/util.cpython-310.pyc
cognet/__pycache__/util.cpython-37.pyc
cognet/__pycache__/util.cpython-39.pyc
cognet/__pycache__/viz.cpython-310.pyc
cognet/__pycache__/viz.cpython-37.pyc
cognet/__pycache__/viz.cpython-39.pyc
cognet/bin/__embed__.so
cognet-0.0.207.dist-info/LICENSE
cognet-0.0.207.dist-info/METADATA
cognet-0.0.207.dist-info/WHEEL
cognet-0.0.207.dist-info/top_level.txt
cognet-0.0.207.dist-info/RECORD
