Metadata-Version: 2.1
Name: cognet
Version: 0.0.207
Summary: Infering Emergent Dependency Structures In Survey Responses
Home-page: https://github.com/zeroknowledgediscovery/cognet
Author: zed.uchicago.edu
Author-email: ishanu@uchicago.edu
License: LICENSE
Download-URL: https://github.com/zeroknowledgediscovery/cognet/archive/0.0.207.tar.gz
Keywords: computational social science,decision trees,machine learning,cognitive dissonance
Platform: UNKNOWN
Classifier: Development Status :: 4 - Beta
Classifier: Intended Audience :: Developers
Classifier: Intended Audience :: Science/Research
Classifier: Topic :: Scientific/Engineering :: Information Analysis
Classifier: Topic :: Software Development :: Libraries
Classifier: License :: OSI Approved :: MIT License
Classifier: Programming Language :: Python :: 3.6
Requires-Python: >=3.6
Requires-Dist: scikit-learn
Requires-Dist: scipy
Requires-Dist: numpy
Requires-Dist: pandas
Requires-Dist: joblib
Requires-Dist: quasinet
